LICENSE
README.md
setup.cfg
setup.py
asyncio_tcp_messages/__init__.py
asyncio_tcp_messages/main.py
asyncio_tcp_messages.egg-info/PKG-INFO
asyncio_tcp_messages.egg-info/SOURCES.txt
asyncio_tcp_messages.egg-info/dependency_links.txt
asyncio_tcp_messages.egg-info/requires.txt
asyncio_tcp_messages.egg-info/top_level.txt