Metadata-Version: 2.1
Name: asyncio-tcp-messages
Version: 0.1.3
Summary: A library for developing applications with a message-based protocol on top of TCP based on asyncio.
Home-page: https://gitlab.com/python-2k2s-2022/asyncio-tasks-submissions/team-4
Author-email: UnMelow@yandex.ru
License: UNKNOWN
Platform: UNKNOWN
Classifier: Programming Language :: Python :: 3.9
Classifier: License :: OSI Approved :: MIT License
Classifier: Operating System :: OS Independent
Requires-Python: >=3.10
License-File: LICENSE
